rigexpert_tool.py
rigexpert_tool-1.0.0.dist-info/DESCRIPTION.rst
rigexpert_tool-1.0.0.dist-info/METADATA
rigexpert_tool-1.0.0.dist-info/RECORD
rigexpert_tool-1.0.0.dist-info/WHEEL
rigexpert_tool-1.0.0.dist-info/entry_points.txt
rigexpert_tool-1.0.0.dist-info/metadata.json
rigexpert_tool-1.0.0.dist-info/top_level.txt
